magic_eden
