Metadata-Version: 2.1
Name: magic-eden-py
Version: 0.0.9
Summary: Python wrap for api solana NFT marketplace MagicEden
Home-page: UNKNOWN
Author: ivan.srshtn.crypto@gmail.com
License: MIT
Project-URL: Source Code, https://github.com/ivannnnnnnnnn/magic-eden-py
Platform: UNKNOWN
License-File: LICENSE
